app_common/__init__.py
app_common/constants.py
app_common/logger.py
app_common/sqs_queues.py
app_common/aws/__init__.py
app_common/aws/aurora.py
app_common/aws/constants.py
app_common/aws/dynamoDB.py
app_common/aws/kinesis.py
app_common/aws/s3.py
app_common/config/__init__.py
app_common/config/base.py
app_common/config/prod.py
app_common/config/stage.py
app_common/database_models/__init__.py
app_common/database_models/common.py
app_common/database_models/support.py
app_common/db/__init__.py
app_common/db/base.py
app_common/db/dialects.py
app_common/db/manager.py
app_common/db/common/__init__.py
app_common/db/common/constants.py
app_common/db/common/custom_fields.py
app_common/db/common/date_time_utils.py
app_common/db/common/tables.py
app_common/db/common/utils.py
app_common/db/helpers/__init__.py
app_common/db/helpers/campaign.py
app_common/db/helpers/common.py
app_common/db/helpers/payments.py
app_common/db/migrations/__init__.py
app_common/db/migrations/migration_0.py
app_common/db/migrations/migration_1.py
app_common/db/migrations/migration_2.py
app_common/db/migrations/migration_3.py
app_common/db/migrations/migration_4.py
app_common/db/migrations/migration_5.py
app_common/db/migrations/runner.py
app_common/db/migrations/data_migration/__init__.py
app_common/db/migrations/data_migration/mappers.py
app_common/db/migrations/data_migration/migrate.py
app_common/db/migrations/data_migration/parser.py
app_common/db/migrations/data_migration/source.py
app_common/db/models/__init__.py
app_common/db/models/brands.py
app_common/db/models/campaigns.py
app_common/db/models/global_model.py
app_common/db/models/history_logs.py
app_common/db/models/migrations.py
app_common/db/models/notifications.py
app_common/db/models/payments.py
app_common/db/models/users.py
app_common/db/models/wrap_schedules.py
app_common/helpers/__init__.py
app_common/helpers/bugs_helpers.py
app_common/helpers/campaigns.py
app_common/helpers/clean_location_data.py
app_common/helpers/csv_helper.py
app_common_libs-1.0.0.dist-info/METADATA
app_common_libs-1.0.0.dist-info/WHEEL
app_common_libs-1.0.0.dist-info/top_level.txt
app_common_libs-1.0.0.dist-info/RECORD
