Metadata-Version: 2.1
Name: app-common-libs
Version: 1.0.0
Summary: Mobilads common libs and functions for backend application
Home-page: 
Author: vikas.goyal
Author-email: vikas@mobilads.co
License: proprietary
Requires-Dist: aiohttp (==3.6.2)
Requires-Dist: async-timeout (==3.0.1)
Requires-Dist: attrs (==19.3.0)
Requires-Dist: aurora-data-api (==0.2.0)
Requires-Dist: blinker (==1.4)
Requires-Dist: certifi (==2019.11.28)
Requires-Dist: chardet (==3.0.4)
Requires-Dist: Click (==7.0)
Requires-Dist: colorama (==0.4.3)
Requires-Dist: docutils (==0.16)
Requires-Dist: dynamorm (==0.9.14)
Requires-Dist: idna (==2.8)
Requires-Dist: iso8601 (==0.1.12)
Requires-Dist: itsdangerous (==1.1.0)
Requires-Dist: jmespath (==0.9.5)
Requires-Dist: MarkupSafe (==1.1.1)
Requires-Dist: marshmallow (==3.6.0)
Requires-Dist: marshmallow-jsonapi (==0.22.0)
Requires-Dist: pyasn1 (==0.4.8)
Requires-Dist: pymysql (==0.9.3)
Requires-Dist: python-dateutil (==2.8.1)
Requires-Dist: PyYAML (==5.3)
Requires-Dist: pytz (==2019.3)
Requires-Dist: requests (==2.22.0)
Requires-Dist: rsa (==4.0)
Requires-Dist: s3transfer (==0.3.3)
Requires-Dist: simplejson (==3.17.0)
Requires-Dist: SQLAlchemy (==1.3.16)
Requires-Dist: six (==1.14.0)
Requires-Dist: stripe (==2.41.1)
Requires-Dist: slackclient (==2.5.0)
Requires-Dist: urllib3 (==1.25.8)
Requires-Dist: Werkzeug (==0.16.1)
Requires-Dist: websocket-client (==0.47.0)
Requires-Dist: yarl (==1.4.2)
